<params><param><value><struct><member><name>SolutionVectors</name><value><array><data><value><struct><member><name>MagValid</name><value><boolean>0</boolean></value></member><member><name>DirValid</name><value><boolean>1</boolean></value></member><member><name>AreaOfOrigin</name><value><struct><member><name>CenterX</name><value><int>280</int></value></member><member><name>CenterY</name><value><int>341</int></value></member><member><name>MajorAxis</name><value><int>103</int></value></member><member><name>MinorAxis</name><value><int>103</int></value></member><member><name>Rotation</name><value><int>0</int></value></member></struct></value></member><member><name>MagnitudeFuzz</name><value><int>0</int></value></member><member><name>Magnitude</name><value><int>1</int></value></member><member><name>DirectionFuzz</name><value><int>3</int></value></member><member><name>Direction</name><value><int>270</int></value></member><member><name>Type</name><value><array><data><value><string>W</string></value></data></array></value></member><member><name>Name</name><value><string>W</string></value></member><member><name>Area</name><value><string>the lifter&apos;s COG</string></value></member></struct></value><value><struct><member><name>MagValid</name><value><boolean>0</boolean></value></member><member><name>DirValid</name><value><boolean>1</boolean></value></member><member><name>AreaOfOrigin</name><value><struct><member><name>CenterX</name><value><int>352</int></value></member><member><name>CenterY</name><value><int>213</int></value></member><member><name>MajorAxis</name><value><int>44</int></value></member><member><name>MinorAxis</name><value><int>44</int></value></member><member><name>Rotation</name><value><int>0</int></value></member></struct></value></member><member><name>MagnitudeFuzz</name><value><int>0</int></value></member><member><name>Magnitude</name><value><int>1</int></value></member><member><name>DirectionFuzz</name><value><int>3</int></value></member><member><name>Direction</name><value><int>270</int></value></member><member><name>Type</name><value><array><data><value><string>F</string></value><value><string>Ry</string></value><value><string>R</string></value></data></array></value></member><member><name>Name</name><value><string>W1</string></value></member><member><name>Area</name><value><string>the left hand</string></value></member></struct></value><value><struct><member><name>MagValid</name><value><boolean>0</boolean></value></member><member><name>DirValid</name><value><boolean>1</boolean></value></member><member><name>AreaOfOrigin</name><value><struct><member><name>CenterX</name><value><int>199</int></value></member><member><name>CenterY</name><value><int>222</int></value></member><member><name>MajorAxis</name><value><int>44</int></value></member><member><name>MinorAxis</name><value><int>44</int></value></member><member><name>Rotation</name><value><int>0</int></value></member></struct></value></member><member><name>MagnitudeFuzz</name><value><int>0</int></value></member><member><name>Magnitude</name><value><int>1</int></value></member><member><name>DirectionFuzz</name><value><int>3</int></value></member><member><name>Direction</name><value><int>270</int></value></member><member><name>Type</name><value><array><data><value><string>F</string></value><value><string>R</string></value><value><string>Ry</string></value></data></array></value></member><member><name>Name</name><value><string>W2</string></value></member><member><name>Area</name><value><string>the right hand</string></value></member></struct></value><value><struct><member><name>MagValid</name><value><boolean>0</boolean></value></member><member><name>DirValid</name><value><boolean>1</boolean></value></member><member><name>AreaOfOrigin</name><value><struct><member><name>CenterX</name><value><int>391</int></value></member><member><name>CenterY</name><value><int>543</int></value></member><member><name>MajorAxis</name><value><int>81</int></value></member><member><name>MinorAxis</name><value><int>34</int></value></member><member><name>Rotation</name><value><int>0</int></value></member></struct></value></member><member><name>MagnitudeFuzz</name><value><int>0</int></value></member><member><name>Magnitude</name><value><int>1</int></value></member><member><name>DirectionFuzz</name><value><int>3</int></value></member><member><name>Direction</name><value><int>90</int></value></member><member><name>Type</name><value><array><data><value><string>N</string></value></data></array></value></member><member><name>Name</name><value><string>R1</string></value></member><member><name>Area</name><value><string>the left foot</string></value></member></struct></value><value><struct><member><name>MagValid</name><value><boolean>0</boolean></value></member><member><name>DirValid</name><value><boolean>1</boolean></value></member><member><name>AreaOfOrigin</name><value><struct><member><name>CenterX</name><value><int>163</int></value></member><member><name>CenterY</name><value><int>554</int></value></member><member><name>MajorAxis</name><value><int>81</int></value></member><member><name>MinorAxis</name><value><int>34</int></value></member><member><name>Rotation</name><value><int>0</int></value></member></struct></value></member><member><name>MagnitudeFuzz</name><value><int>0</int></value></member><member><name>Magnitude</name><value><int>1</int></value></member><member><name>DirectionFuzz</name><value><int>3</int></value></member><member><name>Direction</name><value><int>90</int></value></member><member><name>Type</name><value><array><data><value><string>N</string></value></data></array></value></member><member><name>Name</name><value><string>R2</string></value></member><member><name>Area</name><value><string>the right foot</string></value></member></struct></value></data></array></value></member><member><name>Instructions</name><value><string>Draw a FBD of the weightlifter at the left.  The weights are evenly distributed and the hands are symmetrically placed on the bar.</string></value></member><member><name>Author</name><value><string>RJR</string></value></member><member><name>ScaleFactor</name><value><int>1</int></value></member><member><name>BgImage</name><value><string>weightlifter2.jpg</string></value></member></struct></value></param></params>